LICENSE
MANIFEST.in
README.md
setup.cfg
setup.py
KCMiddleware/KC_exceptions.py
KCMiddleware/KC_middleware.py
KCMiddleware/KC_models.py
KCMiddleware/KC_utils.py
KCMiddleware/__init__.py
KCMiddleware.egg-info/PKG-INFO
KCMiddleware.egg-info/SOURCES.txt
KCMiddleware.egg-info/dependency_links.txt
KCMiddleware.egg-info/requires.txt
KCMiddleware.egg-info/top_level.txt