Metadata-Version: 2.1
Name: KCMiddleware
Version: 0.5
Summary: A Keycloak Middleware
Home-page: https://gitlab.com/ely-zeus/
Author: Alessandro Buffoli
Author-email: alessandro.buffoli@evaspa.it
License: MIT
Download-URL: https://gitlab.com/ely-zeus/keycloak-middleware-package
Keywords: KEYCLOAK,MIDDLEWARE,DJANGO
Platform: UNKNOWN
Classifier: Development Status :: 3 - Alpha
Classifier: Intended Audience :: Developers
Classifier: Topic :: Software Development :: Build Tools
Classifier: License :: OSI Approved :: MIT License
Classifier: Programming Language :: Python :: 3
Classifier: Programming Language :: Python :: 3.6
Classifier: Programming Language :: Python :: 3.7
Classifier: Programming Language :: Python :: 3.8
